LICENSE
MANIFEST.in
README.md
pyproject.toml
setup.cfg
setup.py
finetuner/__init__.py
finetuner/callback.py
finetuner/console.py
finetuner/constants.py
finetuner/data.py
finetuner/excepts.py
finetuner/experiment.py
finetuner/finetuner.py
finetuner/hubble.py
finetuner/model.py
finetuner/names.py
finetuner/run.py
finetuner.egg-info/PKG-INFO
finetuner.egg-info/SOURCES.txt
finetuner.egg-info/dependency_links.txt
finetuner.egg-info/not-zip-safe
finetuner.egg-info/requires.txt
finetuner.egg-info/top_level.txt
finetuner/client/__init__.py
finetuner/client/base.py
finetuner/client/client.py
finetuner/client/session.py