Metadata-Version: 2.1
Name: finetuner
Version: 0.8.0
Summary: Task-oriented finetuning for better embeddings on neural search.
Home-page: https://github.com/jina-ai/finetuner/
Author: Jina AI
Author-email: hello@jina.ai
License: Apache 2.0
Download-URL: https://github.com/jina-ai/finetuner/tags
Project-URL: Documentation, https://finetuner.jina.ai
Project-URL: Source, https://github.com/jina-ai/finetuner/
Project-URL: Tracker, https://github.com/jina-ai/finetuner/issues
Keywords: jina neural-search neural-network deep-learning pretraining fine-tuning pretrained-models triplet-loss metric-learning siamese-network few-shot-learning
Platform: UNKNOWN
Classifier: Development Status :: 5 - Production/Stable
Classifier: Intended Audience :: Developers
Classifier: Intended Audience :: Education
Classifier: Intended Audience :: Science/Research
Classifier: Programming Language :: Python :: 3.8
Classifier: Programming Language :: Python :: 3.9
Classifier: Programming Language :: Python :: 3.10
Classifier: License :: OSI Approved :: Apache Software License
Classifier: Environment :: Console
Classifier: Operating System :: OS Independent
Classifier: Topic :: Scientific/Engineering :: Artificial Intelligence
Requires-Python: >=3.8.0
Provides-Extra: full
Provides-Extra: test
